{"otherData": {},"traceEvents":[{},{"cat":"function","dur":2196961,"name":"glfwInit","ph":"X","pid":0,"tid":10112,"ts":601830945338.500},{"cat":"function","dur":5567944,"name":"glfwCreateWindow","ph":"X","pid":0,"tid":10112,"ts":601834096738.200},{"cat":"function","dur":328655,"name":"void __cdecl Hazel::OpenGLContext::Init(void)","ph":"X","pid":0,"tid":10112,"ts":601839757285.500},{"cat":"function","dur":19,"name":"void __cdecl Hazel::WindowsWindow::SetVSync(bool)","ph":"X","pid":0,"tid":10112,"ts":601840086875.000},{"cat":"function","dur":9171712,"name":"void __cdecl Hazel::WindowsWindow::Init(const struct Hazel::WindowProps &)","ph":"X","pid":0,"tid":10112,"ts":601830915275.800},{"cat":"function","dur":9196059,"name":"__cdecl Hazel::WindowsWindow::WindowsWindow(const struct Hazel::WindowProps &)","ph":"X","pid":0,"tid":10112,"ts":601830891347.300},{"cat":"function","dur":79915,"name":"void __cdecl Hazel::OpenGLRendererAPI::Init(void)","ph":"X","pid":0,"tid":10112,"ts":601840137930.400},{"cat":"function","dur":4052,"name":"__cdecl Hazel::OpenGLVertexArray::OpenGLVertexArray(void)","ph":"X","pid":0,"tid":10112,"ts":601840218986.200},{"cat":"function","dur":4629,"name":"__cdecl Hazel::OpenGLVertexBuffer::OpenGLVertexBuffer(unsigned int)","ph":"X","pid":0,"tid":10112,"ts":601840250203.600},{"cat":"function","dur":1,"name":"void __cdecl Hazel::OpenGLVertexBuffer::Bind(void) const","ph":"X","pid":0,"tid":10112,"ts":601840273690.100},{"cat":"function","dur":41152,"name":"void __cdecl Hazel::OpenGLVertexArray::AddVertexBuffer(const class std::shared_ptr<class Hazel::VertexBuffer> &)","ph":"X","pid":0,"tid":10112,"ts":601840273670.100},{"cat":"function","dur":6058,"name":"__cdecl Hazel::OpenGLIndexBuffer::OpenGLIndexBuffer(unsigned int *,unsigned int)","ph":"X","pid":0,"tid":10112,"ts":601840315470.300},{"cat":"function","dur":16,"name":"void __cdecl Hazel::OpenGLIndexBuffer::Bind(void) const","ph":"X","pid":0,"tid":10112,"ts":601840322670.700},{"cat":"function","dur":935,"name":"void __cdecl Hazel::OpenGLVertexArray::SetIndexBuffer(const class std::shared_ptr<class Hazel::IndexBuffer> &)","ph":"X","pid":0,"tid":10112,"ts":601840322041.500},{"cat":"function","dur":42075,"name":"__cdecl Hazel::OpenGLTexture2D::OpenGLTexture2D(unsigned int,unsigned int)","ph":"X","pid":0,"tid":10112,"ts":601840323072.800},{"cat":"function","dur":45388,"name":"void __cdecl Hazel::OpenGLTexture2D::SetData(void *,unsigned int)","ph":"X","pid":0,"tid":10112,"ts":601840366510.300},{"cat":"function","dur":39564,"name":"class std::basic_string<char,struct std::char_traits<char>,class std::allocator<char> > __cdecl Hazel::OpenGLShader::ReadFile(const class std::basic_string<char,struct std::char_traits<char>,class std::allocator<char> > &)","ph":"X","pid":0,"tid":10112,"ts":601840446860.100},{"cat":"function","dur":268,"name":"class std::unordered_map<unsigned int,class std::basic_string<char,struct std::char_traits<char>,class std::allocator<char> >,struct std::hash<unsigned int>,struct std::equal_to<unsigned int>,class std::allocator<struct std::pair<unsigned int const ,class std::basic_string<char,struct std::char_traits<char>,class std::allocator<char> > > > > __cdecl Hazel::OpenGLShader::PreProcess(const class std::basic_string<char,struct std::char_traits<char>,class std::allocator<char> > &)","ph":"X","pid":0,"tid":10112,"ts":601840486637.200},{"cat":"function","dur":2308188,"name":"void __cdecl Hazel::OpenGLShader::Compile(const class std::unordered_map<unsigned int,class std::basic_string<char,struct std::char_traits<char>,class std::allocator<char> >,struct std::hash<unsigned int>,struct std::equal_to<unsigned int>,class std::allocator<struct std::pair<unsigned int const ,class std::basic_string<char,struct std::char_traits<char>,class std::allocator<char> > > > > &)","ph":"X","pid":0,"tid":10112,"ts":601840486989.000},{"cat":"function","dur":2374309,"name":"__cdecl Hazel::OpenGLShader::OpenGLShader(const class std::basic_string<char,struct std::char_traits<char>,class std::allocator<char> > &)","ph":"X","pid":0,"tid":10112,"ts":601840446851.600},{"cat":"function","dur":121402,"name":"void __cdecl Hazel::OpenGLShader::Bind(void) const","ph":"X","pid":0,"tid":10112,"ts":601842821810.200},{"cat":"function","dur":2727006,"name":"void __cdecl Hazel::Renderer2D::Init(void)","ph":"X","pid":0,"tid":10112,"ts":601840218156.500},{"cat":"function","dur":2817214,"name":"void __cdecl Hazel::Renderer::Init(void)","ph":"X","pid":0,"tid":10112,"ts":601840128047.800},{"cat":"function","dur":52091,"name":"void __cdecl Hazel::ImGuiLayer::OnAttach(void)","ph":"X","pid":0,"tid":10112,"ts":601842985190.500},{"cat":"function","dur":52655,"name":"void __cdecl Hazel::Application::PushOverlay(class Hazel::Layer *)","ph":"X","pid":0,"tid":10112,"ts":601842984856.700},{"cat":"function","dur":12148246,"name":"__cdecl Hazel::Application::Application(void)","ph":"X","pid":0,"tid":10112,"ts":601830889394.500},{"cat":"function","dur":5,"name":"__cdecl Hazel::OrthographicCamera::OrthographicCamera(float,float,float,float)","ph":"X","pid":0,"tid":10112,"ts":601843037786.900},{"cat":"function","dur":19140,"name":"stbi_load - OpenGLTexture2D::OpenGLTexture2D(const std:string&)","ph":"X","pid":0,"tid":10112,"ts":601843064157.600},{"cat":"function","dur":106410,"name":"__cdecl Hazel::OpenGLTexture2D::OpenGLTexture2D(const class std::basic_string<char,struct std::char_traits<char>,class std::allocator<char> > &)","ph":"X","pid":0,"tid":10112,"ts":601843063660.200},{"cat":"function","dur":106663,"name":"void __cdecl Sandbox2D::OnAttach(void)","ph":"X","pid":0,"tid":10112,"ts":601843063639.700},{"cat":"function","dur":132465,"name":"void __cdecl Hazel::Application::PushLayer(class Hazel::Layer *)","ph":"X","pid":0,"tid":10112,"ts":601843037889.600}]}